cluster_model/__init__.py
cluster_model/river_class.py
cluster_model-0.1.dist-info/LICENSE.MD
cluster_model-0.1.dist-info/METADATA
cluster_model-0.1.dist-info/WHEEL
cluster_model-0.1.dist-info/top_level.txt
cluster_model-0.1.dist-info/RECORD
