Metadata-Version: 2.1
Name: cluster-model
Version: 0.1
Summary: Class for wrapping a cluster model from the river package for BERTopic Online Topic Modeling
Home-page: https://github.com/denaldo98/cluster_model
Author: Denaldo Lapi
Author-email: denaldo98@gmail.com
License: MIT
License-File: LICENSE.MD
Requires-Dist: river
